bondzai.gateway_sdk-0.0.21-py3.10-nspkg.pth
bondzai/gateway_sdk/__init__.py
bondzai/gateway_sdk/agent.py
bondzai/gateway_sdk/commands.py
bondzai/gateway_sdk/config.py
bondzai/gateway_sdk/enums.py
bondzai/gateway_sdk/events.py
bondzai/gateway_sdk/gateway.py
bondzai/gateway_sdk/message.py
bondzai/gateway_sdk/request.py
bondzai/gateway_sdk/responses.py
bondzai/gateway_sdk/timer.py
bondzai/gateway_sdk/transcode.py
bondzai/gateway_sdk/utils.py
bondzai.gateway_sdk-0.0.21.dist-info/METADATA
bondzai.gateway_sdk-0.0.21.dist-info/NOTICE
bondzai.gateway_sdk-0.0.21.dist-info/WHEEL
bondzai.gateway_sdk-0.0.21.dist-info/namespace_packages.txt
bondzai.gateway_sdk-0.0.21.dist-info/top_level.txt
bondzai.gateway_sdk-0.0.21.dist-info/zip-safe
bondzai.gateway_sdk-0.0.21.dist-info/RECORD
